{
  "name": "Calm",
  "author": "Shubham",
  "dark": true,
  "editorScheme": "/themes/calm.xml",
  "colors": {
    "background": "#223844FF",
    "selectionBackground": "#3F4E57",
    "hover": "#4F5D5E"
  },
  "ui": {
    "*": {
      "background": "background",
      "foreground": "#D6DEEB",
      "highlight": "#425b67ff",
      "selectionBackground": "#4373C2",
      "selectionInactiveBackground": "#4373C2",
      "selectionForeground": "#ffffffff",
      "button": "#2e3c43ff",
      "secondaryBackground": "#32424aff",
      "disabled": "#415967ff",
      "contrast": "#1e272cff",
      "tableSelected": "#314549ff",
      "secondBorder": "#2a373eff",
      "treeSelection": "#00485c",
      "notifications": "#323232ff",
      "accent": "#009688ff",
      "excluded": "#4373C2"
    },
    "Islands": 1,
    "Island": {
      "arc": 20,
      "borderWidth": 6,
      "borderColor": "background",
      "inactiveAlpha": 0.44,
      "inactiveAlphaInStatusBar": {
        "os.mac": 0.2,
        "os.windows": 0.2,
        "os.linux": 0.15
      }
    },
    "MainWindow.background": "selectionBackground",
    "DefaultTabs": {
      "background": "background",
      "borderColor": "background"
    },
    "EditorTabs": {
      "background": "background",
      "underTabsBorderColor": "background",

      "underlinedTabBackground": "selectionBackground",
      "underlinedBorderColor": "selectionBackground",

      "inactiveUnderlinedTabBackground": "selectionBackground",
      "inactiveUnderlinedTabBorderColor": "selectionBackground",

      "hoverBackground": "hover",

      "tabInsets": "-6,8,-6,8",
      "tabInsets.compact": "-2,6,-2,4",
      "tabContentActionsRightInsets": "0,2,0,2"
    },
    "ToolWindow": {
      "Header": {
        "inactiveBackground": "background",
        "background": "background"
      },
      "background": "background"
    },
    "Plugins": {
      "Button": {
        "installBackground": "#26324fff",
        "updateBackground": "#26324fff",
        "installForeground": "#ffffff",
        "installFillForeground": "#ffffff",
        "updateForeground": "#ffffff"
      }
    },
    "Popup": {
      "Header.activeBackground": "background"
    },
    "TabbedPane": {
      "hoverColor": "#002441"
    },
    "Button": {
      "focus": "#002441"
    },
    "ActionButton": {
      "hoverBackground": "hover",
      "hoverBorderColor": "background",
      "pressedBackground": "background",
      "pressedBorderColor": "background"
    }
  }
}